odoo10_addon_base_business_document_import_phone-10.0.1.0.0-py2.7-nspkg.pth
odoo/addons/base_business_document_import_phone/README.rst
odoo/addons/base_business_document_import_phone/__init__.py
odoo/addons/base_business_document_import_phone/__manifest__.py
odoo/addons/base_business_document_import_phone/models/__init__.py
odoo/addons/base_business_document_import_phone/models/business_document_import.py
odoo/addons/base_business_document_import_phone/tests/__init__.py
odoo/addons/base_business_document_import_phone/tests/test_phone_partner_match.py
odoo10_addon_base_business_document_import_phone-10.0.1.0.0.dist-info/DESCRIPTION.rst
odoo10_addon_base_business_document_import_phone-10.0.1.0.0.dist-info/METADATA
odoo10_addon_base_business_document_import_phone-10.0.1.0.0.dist-info/RECORD
odoo10_addon_base_business_document_import_phone-10.0.1.0.0.dist-info/WHEEL
odoo10_addon_base_business_document_import_phone-10.0.1.0.0.dist-info/metadata.json
odoo10_addon_base_business_document_import_phone-10.0.1.0.0.dist-info/namespace_packages.txt
odoo10_addon_base_business_document_import_phone-10.0.1.0.0.dist-info/top_level.txt
