Metadata-Version: 2.0
Name: odoo10-addon-base-business-document-import-phone
Version: 10.0.1.0.0
Summary: Use phone numbers to match partners upon import of business documents
Home-page: http://www.akretion.com
Author: Akretion,Odoo Community Association (OCA)
Author-email: support@odoo-community.org
License: AGPL-3
Platform: UNKNOWN
Classifier: Programming Language :: Python :: 2.7
Classifier: Framework :: Odoo
Classifier: License :: OSI Approved :: GNU Affero General Public License v3
Requires-Dist: odoo (<10.1dev,>=10.0)
Requires-Dist: odoo10-addon-base-business-document-import
Requires-Dist: odoo10-addon-base-phone
